nested_dask/__init__.py
nested_dask/_version.py
nested_dask/accessor.py
nested_dask/backends.py
nested_dask/core.py
nested_dask/io.py
nested_dask/py.typed
nested_dask/datasets/__init__.py
nested_dask/datasets/generation.py
nested_dask/utils/__init__.py
nested_dask/utils/utils.py
nested_dask-0.3.4.dist-info/LICENSE
nested_dask-0.3.4.dist-info/METADATA
nested_dask-0.3.4.dist-info/WHEEL
nested_dask-0.3.4.dist-info/top_level.txt
nested_dask-0.3.4.dist-info/RECORD
