Metadata-Version: 2.2
Name: nested-dask
Version: 0.3.4
Summary: Parallel nested-pandas with Dask.
Author-email: lincc-frameworks <brantd@uw.edu>
License: MIT License
Project-URL: Source Code, https://github.com/lincc-frameworks/nested-dask
Classifier: Development Status :: 4 - Beta
Classifier: License :: OSI Approved :: MIT License
Classifier: Intended Audience :: Developers
Classifier: Intended Audience :: Science/Research
Classifier: Operating System :: OS Independent
Classifier: Programming Language :: Python
Requires-Python: >=3.10
License-File: LICENSE
Requires-Dist: nested-pandas<0.4.0,>=0.3.1
Requires-Dist: numpy
Requires-Dist: dask>=2025.1.0
Requires-Dist: dask[distributed]>=2025.2.0
Requires-Dist: pyarrow
Provides-Extra: dev
Requires-Dist: asv==0.6.4; extra == "dev"
Requires-Dist: jupyter; extra == "dev"
Requires-Dist: mypy; extra == "dev"
Requires-Dist: pre-commit; extra == "dev"
Requires-Dist: pytest; extra == "dev"
Requires-Dist: pytest-cov; extra == "dev"
Requires-Dist: ruff; extra == "dev"
Requires-Dist: aiohttp; extra == "dev"
